gnosis/__init__.py
gnosis/py.typed
gnosis/eth/__init__.py
gnosis/eth/constants.py
gnosis/eth/ethereum_client.py
gnosis/eth/typing.py
gnosis/eth/utils.py
gnosis/eth/clients/__init__.py
gnosis/eth/clients/blockscout_client.py
gnosis/eth/clients/contract_metadata.py
gnosis/eth/clients/etherscan_client.py
gnosis/eth/clients/sourcify.py
gnosis/eth/contracts/CPKFactory.json
gnosis/eth/contracts/DelegateConstructorProxy.json
gnosis/eth/contracts/ERC20.json
gnosis/eth/contracts/ERC20TestToken.json
gnosis/eth/contracts/ERC721.json
gnosis/eth/contracts/GnosisSafe_V0_0_1.json
gnosis/eth/contracts/GnosisSafe_V1_0_0.json
gnosis/eth/contracts/GnosisSafe_V1_1_1.json
gnosis/eth/contracts/GnosisSafe_V1_3_0.json
gnosis/eth/contracts/MultiSend.json
gnosis/eth/contracts/PayingProxy.json
gnosis/eth/contracts/ProxyFactory_V1_0_0.json
gnosis/eth/contracts/ProxyFactory_V1_1_1.json
gnosis/eth/contracts/ProxyFactory_V1_3_0.json
gnosis/eth/contracts/Proxy_V1_0_0.json
gnosis/eth/contracts/Proxy_V1_1_1.json
gnosis/eth/contracts/__init__.py
gnosis/eth/contracts/kyber_network_proxy.json
gnosis/eth/contracts/uniswap_exchange.json
gnosis/eth/contracts/uniswap_factory.json
gnosis/eth/contracts/uniswap_v2_factory.json
gnosis/eth/contracts/uniswap_v2_pair.json
gnosis/eth/contracts/uniswap_v2_router.json
gnosis/eth/django/__init__.py
gnosis/eth/django/filters.py
gnosis/eth/django/models.py
gnosis/eth/django/serializers.py
gnosis/eth/django/validators.py
gnosis/eth/django/tests/__init__.py
gnosis/eth/django/tests/models.py
gnosis/eth/django/tests/test_models.py
gnosis/eth/django/tests/test_serializers.py
gnosis/eth/django/tests/test_validators.py
gnosis/eth/oracles/__init__.py
gnosis/eth/oracles/oracles.py
gnosis/eth/oracles/abis/__init__.py
gnosis/eth/oracles/abis/aave_abis.py
gnosis/eth/oracles/abis/balancer_abis.py
gnosis/eth/oracles/abis/curve_abis.py
gnosis/eth/oracles/abis/mooniswap_abis.py
gnosis/eth/oracles/abis/yearn_abis.py
gnosis/eth/oracles/abis/zerion_abis.py
gnosis/eth/tests/__init__.py
gnosis_py_sovryn-3.2.5.dist-info/LICENSE
gnosis_py_sovryn-3.2.5.dist-info/METADATA
gnosis_py_sovryn-3.2.5.dist-info/WHEEL
gnosis_py_sovryn-3.2.5.dist-info/top_level.txt
gnosis_py_sovryn-3.2.5.dist-info/RECORD
