Metadata-Version: 2.1
Name: gnosis-py-sovryn
Version: 3.2.5
Summary: Gnosis libraries for Python Projects
Home-page: https://github.com/DistributedCollective/gnosis-py
Author: Uxío
Author-email: uxio@gnosis.pm
License: MIT License
Keywords: ethereum,django,rest,gnosis
Platform: UNKNOWN
Classifier: Environment :: Web Environment
Classifier: Framework :: Django
Classifier: Framework :: Django :: 2.0
Classifier: Intended Audience :: Developers
Classifier: License :: OSI Approved :: MIT License
Classifier: Operating System :: OS Independent
Classifier: Programming Language :: Python
Classifier: Programming Language :: Python :: 3.7
Classifier: Programming Language :: Python :: 3.8
Classifier: Programming Language :: Python :: 3.9
Classifier: Topic :: Internet :: WWW/HTTP
Classifier: Topic :: Internet :: WWW/HTTP :: Dynamic Content
Requires-Python: >=3.7
License-File: LICENSE
Requires-Dist: ethereum (>=2.3.2)
Requires-Dist: packaging
Requires-Dist: py-eth-sig-utils (>=0.3.0)
Requires-Dist: requests (>=2)
Requires-Dist: web3 (>=5.23.0)
Requires-Dist: cached-property (>=1.5) ; python_version < "3.8"
Requires-Dist: typing-extensions (==3.10.0.0) ; python_version < "3.8"
Provides-Extra: django
Requires-Dist: django (>=2) ; extra == 'django'
Requires-Dist: django-filter (>=2) ; extra == 'django'
Requires-Dist: djangorestframework (>=2) ; extra == 'django'
